{
  "start": "2024-09-06",
  "end": "2024-09-13",
  "package": "d3-time-format",
  "downloads": [
    {
      "downloads": 1175372,
      "day": "2024-09-06"
    },
    {
      "downloads": 248664,
      "day": "2024-09-07"
    },
    {
      "downloads": 253372,
      "day": "2024-09-08"
    },
    {
      "downloads": 1296323,
      "day": "2024-09-09"
    },
    {
      "downloads": 1352556,
      "day": "2024-09-10"
    },
    {
      "downloads": 1345209,
      "day": "2024-09-11"
    },
    {
      "downloads": 1364678,
      "day": "2024-09-12"
    },
    {
      "downloads": 1140250,
      "day": "2024-09-13"
    }
  ]
}