{
  "start": "2024-09-01",
  "end": "2024-09-08",
  "package": "highcharts",
  "downloads": [
    {
      "downloads": 37793,
      "day": "2024-09-01"
    },
    {
      "downloads": 174280,
      "day": "2024-09-02"
    },
    {
      "downloads": 243195,
      "day": "2024-09-03"
    },
    {
      "downloads": 245368,
      "day": "2024-09-04"
    },
    {
      "downloads": 240464,
      "day": "2024-09-05"
    },
    {
      "downloads": 196339,
      "day": "2024-09-06"
    },
    {
      "downloads": 31319,
      "day": "2024-09-07"
    },
    {
      "downloads": 33241,
      "day": "2024-09-08"
    }
  ]
}