{
  "start": "2024-10-08",
  "end": "2024-10-15",
  "package": "recharts",
  "downloads": [
    {
      "downloads": 402924,
      "day": "2024-10-08"
    },
    {
      "downloads": 406972,
      "day": "2024-10-09"
    },
    {
      "downloads": 395614,
      "day": "2024-10-10"
    },
    {
      "downloads": 335224,
      "day": "2024-10-11"
    },
    {
      "downloads": 77719,
      "day": "2024-10-12"
    },
    {
      "downloads": 83008,
      "day": "2024-10-13"
    },
    {
      "downloads": 357345,
      "day": "2024-10-14"
    },
    {
      "downloads": 409124,
      "day": "2024-10-15"
    }
  ]
}