{
  "start": "2024-09-01",
  "end": "2024-09-08",
  "package": "d3-fetch",
  "downloads": [
    {
      "downloads": 101307,
      "day": "2024-09-01"
    },
    {
      "downloads": 342577,
      "day": "2024-09-02"
    },
    {
      "downloads": 471700,
      "day": "2024-09-03"
    },
    {
      "downloads": 499599,
      "day": "2024-09-04"
    },
    {
      "downloads": 487119,
      "day": "2024-09-05"
    },
    {
      "downloads": 428022,
      "day": "2024-09-06"
    },
    {
      "downloads": 98697,
      "day": "2024-09-07"
    },
    {
      "downloads": 97527,
      "day": "2024-09-08"
    }
  ]
}