{
  "start": "2024-09-23",
  "end": "2024-09-30",
  "package": "d3-fetch",
  "downloads": [
    {
      "downloads": 467214,
      "day": "2024-09-23"
    },
    {
      "downloads": 507564,
      "day": "2024-09-24"
    },
    {
      "downloads": 476236,
      "day": "2024-09-25"
    },
    {
      "downloads": 482239,
      "day": "2024-09-26"
    },
    {
      "downloads": 416603,
      "day": "2024-09-27"
    },
    {
      "downloads": 96950,
      "day": "2024-09-28"
    },
    {
      "downloads": 95118,
      "day": "2024-09-29"
    },
    {
      "downloads": 459911,
      "day": "2024-09-30"
    }
  ]
}