{
  "start": "2023-09-22",
  "end": "2024-09-22",
  "package": "echarts",
  "downloads": [
    {
      "downloads": 112621,
      "day": "2023-09-22"
    },
    {
      "downloads": 94911,
      "day": "2023-09-29"
    },
    {
      "downloads": 99090,
      "day": "2023-10-06"
    },
    {
      "downloads": 120228,
      "day": "2023-10-13"
    },
    {
      "downloads": 122362,
      "day": "2023-10-20"
    },
    {
      "downloads": 118738,
      "day": "2023-10-27"
    },
    {
      "downloads": 0,
      "day": "2023-11-03"
    },
    {
      "downloads": 108278,
      "day": "2023-11-10"
    },
    {
      "downloads": 114152,
      "day": "2023-11-17"
    },
    {
      "downloads": 102634,
      "day": "2023-11-24"
    },
    {
      "downloads": 125720,
      "day": "2023-12-01"
    },
    {
      "downloads": 113796,
      "day": "2023-12-08"
    },
    {
      "downloads": 110428,
      "day": "2023-12-15"
    },
    {
      "downloads": 90836,
      "day": "2023-12-22"
    },
    {
      "downloads": 64012,
      "day": "2023-12-29"
    },
    {
      "downloads": 100313,
      "day": "2024-01-05"
    },
    {
      "downloads": 108683,
      "day": "2024-01-12"
    },
    {
      "downloads": 114526,
      "day": "2024-01-19"
    },
    {
      "downloads": 112674,
      "day": "2024-01-26"
    },
    {
      "downloads": 124385,
      "day": "2024-02-02"
    },
    {
      "downloads": 108633,
      "day": "2024-02-09"
    },
    {
      "downloads": 112091,
      "day": "2024-02-16"
    },
    {
      "downloads": 130381,
      "day": "2024-02-23"
    },
    {
      "downloads": 147639,
      "day": "2024-03-01"
    },
    {
      "downloads": 134526,
      "day": "2024-03-08"
    },
    {
      "downloads": 123571,
      "day": "2024-03-15"
    },
    {
      "downloads": 140083,
      "day": "2024-03-22"
    },
    {
      "downloads": 101001,
      "day": "2024-03-29"
    },
    {
      "downloads": 116204,
      "day": "2024-04-05"
    },
    {
      "downloads": 137149,
      "day": "2024-04-12"
    },
    {
      "downloads": 133382,
      "day": "2024-04-19"
    },
    {
      "downloads": 141817,
      "day": "2024-04-26"
    },
    {
      "downloads": 122087,
      "day": "2024-05-03"
    },
    {
      "downloads": 126551,
      "day": "2024-05-10"
    },
    {
      "downloads": 143049,
      "day": "2024-05-17"
    },
    {
      "downloads": 152587,
      "day": "2024-05-24"
    },
    {
      "downloads": 140034,
      "day": "2024-05-31"
    },
    {
      "downloads": 133147,
      "day": "2024-06-07"
    },
    {
      "downloads": 125359,
      "day": "2024-06-14"
    },
    {
      "downloads": 131639,
      "day": "2024-06-21"
    },
    {
      "downloads": 136936,
      "day": "2024-06-28"
    },
    {
      "downloads": 121881,
      "day": "2024-07-05"
    },
    {
      "downloads": 147275,
      "day": "2024-07-12"
    },
    {
      "downloads": 137157,
      "day": "2024-07-19"
    },
    {
      "downloads": 145185,
      "day": "2024-07-26"
    },
    {
      "downloads": 144835,
      "day": "2024-08-02"
    },
    {
      "downloads": 151502,
      "day": "2024-08-09"
    },
    {
      "downloads": 132333,
      "day": "2024-08-16"
    },
    {
      "downloads": 147710,
      "day": "2024-08-23"
    },
    {
      "downloads": 140209,
      "day": "2024-08-30"
    },
    {
      "downloads": 159436,
      "day": "2024-09-06"
    },
    {
      "downloads": 149188,
      "day": "2024-09-13"
    },
    {
      "downloads": 161173,
      "day": "2024-09-20"
    }
  ]
}