{
  "start": "2025-04-25",
  "end": "2025-05-02",
  "package": "@swc/core",
  "downloads": [
    {
      "downloads": 2062202,
      "day": "2025-04-25"
    },
    {
      "downloads": 634943,
      "day": "2025-04-26"
    },
    {
      "downloads": 670300,
      "day": "2025-04-27"
    },
    {
      "downloads": 2213306,
      "day": "2025-04-28"
    },
    {
      "downloads": 2339062,
      "day": "2025-04-29"
    },
    {
      "downloads": 2307570,
      "day": "2025-04-30"
    },
    {
      "downloads": 1652840,
      "day": "2025-05-01"
    },
    {
      "downloads": 1856051,
      "day": "2025-05-02"
    }
  ]
}