{
  "start": "2024-12-20",
  "end": "2024-12-27",
  "package": "@visx/clip-path",
  "downloads": [
    {
      "downloads": 13627,
      "day": "2024-12-20"
    },
    {
      "downloads": 2363,
      "day": "2024-12-21"
    },
    {
      "downloads": 1499,
      "day": "2024-12-22"
    },
    {
      "downloads": 7863,
      "day": "2024-12-23"
    },
    {
      "downloads": 5002,
      "day": "2024-12-24"
    },
    {
      "downloads": 1934,
      "day": "2024-12-25"
    },
    {
      "downloads": 3702,
      "day": "2024-12-26"
    },
    {
      "downloads": 4344,
      "day": "2024-12-27"
    }
  ]
}