{
  "start": "2023-09-22",
  "end": "2024-09-22",
  "package": "@visx/threshold",
  "downloads": [
    {
      "downloads": 4062,
      "day": "2023-09-22"
    },
    {
      "downloads": 5115,
      "day": "2023-09-29"
    },
    {
      "downloads": 4417,
      "day": "2023-10-06"
    },
    {
      "downloads": 4538,
      "day": "2023-10-13"
    },
    {
      "downloads": 4989,
      "day": "2023-10-20"
    },
    {
      "downloads": 4226,
      "day": "2023-10-27"
    },
    {
      "downloads": 0,
      "day": "2023-11-03"
    },
    {
      "downloads": 4765,
      "day": "2023-11-10"
    },
    {
      "downloads": 5046,
      "day": "2023-11-17"
    },
    {
      "downloads": 3285,
      "day": "2023-11-24"
    },
    {
      "downloads": 5198,
      "day": "2023-12-01"
    },
    {
      "downloads": 5571,
      "day": "2023-12-08"
    },
    {
      "downloads": 5431,
      "day": "2023-12-15"
    },
    {
      "downloads": 3783,
      "day": "2023-12-22"
    },
    {
      "downloads": 2081,
      "day": "2023-12-29"
    },
    {
      "downloads": 4623,
      "day": "2024-01-05"
    },
    {
      "downloads": 5639,
      "day": "2024-01-12"
    },
    {
      "downloads": 5476,
      "day": "2024-01-19"
    },
    {
      "downloads": 7025,
      "day": "2024-01-26"
    },
    {
      "downloads": 6906,
      "day": "2024-02-02"
    },
    {
      "downloads": 7107,
      "day": "2024-02-09"
    },
    {
      "downloads": 6597,
      "day": "2024-02-16"
    },
    {
      "downloads": 6048,
      "day": "2024-02-23"
    },
    {
      "downloads": 10195,
      "day": "2024-03-01"
    },
    {
      "downloads": 7001,
      "day": "2024-03-08"
    },
    {
      "downloads": 7566,
      "day": "2024-03-15"
    },
    {
      "downloads": 7229,
      "day": "2024-03-22"
    },
    {
      "downloads": 4841,
      "day": "2024-03-29"
    },
    {
      "downloads": 6541,
      "day": "2024-04-05"
    },
    {
      "downloads": 6988,
      "day": "2024-04-12"
    },
    {
      "downloads": 9694,
      "day": "2024-04-19"
    },
    {
      "downloads": 7873,
      "day": "2024-04-26"
    },
    {
      "downloads": 9063,
      "day": "2024-05-03"
    },
    {
      "downloads": 9502,
      "day": "2024-05-10"
    },
    {
      "downloads": 8932,
      "day": "2024-05-17"
    },
    {
      "downloads": 9097,
      "day": "2024-05-24"
    },
    {
      "downloads": 11392,
      "day": "2024-05-31"
    },
    {
      "downloads": 10405,
      "day": "2024-06-07"
    },
    {
      "downloads": 9375,
      "day": "2024-06-14"
    },
    {
      "downloads": 6071,
      "day": "2024-06-21"
    },
    {
      "downloads": 5305,
      "day": "2024-06-28"
    },
    {
      "downloads": 4690,
      "day": "2024-07-05"
    },
    {
      "downloads": 5916,
      "day": "2024-07-12"
    },
    {
      "downloads": 6256,
      "day": "2024-07-19"
    },
    {
      "downloads": 5884,
      "day": "2024-07-26"
    },
    {
      "downloads": 6743,
      "day": "2024-08-02"
    },
    {
      "downloads": 6362,
      "day": "2024-08-09"
    },
    {
      "downloads": 6749,
      "day": "2024-08-16"
    },
    {
      "downloads": 7796,
      "day": "2024-08-23"
    },
    {
      "downloads": 5915,
      "day": "2024-08-30"
    },
    {
      "downloads": 7112,
      "day": "2024-09-06"
    },
    {
      "downloads": 6568,
      "day": "2024-09-13"
    },
    {
      "downloads": 5604,
      "day": "2024-09-20"
    }
  ]
}