{
  "start": "2024-09-26",
  "end": "2024-10-03",
  "package": "@visx/zoom",
  "downloads": [
    {
      "downloads": 12510,
      "day": "2024-09-26"
    },
    {
      "downloads": 10344,
      "day": "2024-09-27"
    },
    {
      "downloads": 1251,
      "day": "2024-09-28"
    },
    {
      "downloads": 1088,
      "day": "2024-09-29"
    },
    {
      "downloads": 13084,
      "day": "2024-09-30"
    },
    {
      "downloads": 11451,
      "day": "2024-10-01"
    },
    {
      "downloads": 9789,
      "day": "2024-10-02"
    },
    {
      "downloads": 9166,
      "day": "2024-10-03"
    }
  ]
}