{
  "start": "2024-12-20",
  "end": "2024-12-27",
  "package": "@visx/voronoi",
  "downloads": [
    {
      "downloads": 27049,
      "day": "2024-12-20"
    },
    {
      "downloads": 6059,
      "day": "2024-12-21"
    },
    {
      "downloads": 5275,
      "day": "2024-12-22"
    },
    {
      "downloads": 18829,
      "day": "2024-12-23"
    },
    {
      "downloads": 11713,
      "day": "2024-12-24"
    },
    {
      "downloads": 6249,
      "day": "2024-12-25"
    },
    {
      "downloads": 12128,
      "day": "2024-12-26"
    },
    {
      "downloads": 11597,
      "day": "2024-12-27"
    }
  ]
}