{
  "start": "2024-09-10",
  "end": "2024-09-17",
  "package": "@visx/tooltip",
  "downloads": [
    {
      "downloads": 72118,
      "day": "2024-09-10"
    },
    {
      "downloads": 68176,
      "day": "2024-09-11"
    },
    {
      "downloads": 71025,
      "day": "2024-09-12"
    },
    {
      "downloads": 60364,
      "day": "2024-09-13"
    },
    {
      "downloads": 10078,
      "day": "2024-09-14"
    },
    {
      "downloads": 8847,
      "day": "2024-09-15"
    },
    {
      "downloads": 67188,
      "day": "2024-09-16"
    },
    {
      "downloads": 65260,
      "day": "2024-09-17"
    }
  ]
}