{
  "start": "2023-11-05",
  "end": "2024-11-05",
  "package": "@visx/tooltip",
  "downloads": [
    {
      "downloads": 9651,
      "day": "2023-11-05"
    },
    {
      "downloads": 8008,
      "day": "2023-11-12"
    },
    {
      "downloads": 7206,
      "day": "2023-11-19"
    },
    {
      "downloads": 7252,
      "day": "2023-11-26"
    },
    {
      "downloads": 8918,
      "day": "2023-12-03"
    },
    {
      "downloads": 6849,
      "day": "2023-12-10"
    },
    {
      "downloads": 9964,
      "day": "2023-12-17"
    },
    {
      "downloads": 4735,
      "day": "2023-12-24"
    },
    {
      "downloads": 6351,
      "day": "2023-12-31"
    },
    {
      "downloads": 6608,
      "day": "2024-01-07"
    },
    {
      "downloads": 6969,
      "day": "2024-01-14"
    },
    {
      "downloads": 10261,
      "day": "2024-01-21"
    },
    {
      "downloads": 9912,
      "day": "2024-01-28"
    },
    {
      "downloads": 11819,
      "day": "2024-02-04"
    },
    {
      "downloads": 8877,
      "day": "2024-02-11"
    },
    {
      "downloads": 9535,
      "day": "2024-02-18"
    },
    {
      "downloads": 8709,
      "day": "2024-02-25"
    },
    {
      "downloads": 11194,
      "day": "2024-03-03"
    },
    {
      "downloads": 8329,
      "day": "2024-03-10"
    },
    {
      "downloads": 9762,
      "day": "2024-03-17"
    },
    {
      "downloads": 8016,
      "day": "2024-03-24"
    },
    {
      "downloads": 6479,
      "day": "2024-03-31"
    },
    {
      "downloads": 10985,
      "day": "2024-04-07"
    },
    {
      "downloads": 8985,
      "day": "2024-04-14"
    },
    {
      "downloads": 12073,
      "day": "2024-04-21"
    },
    {
      "downloads": 13105,
      "day": "2024-04-28"
    },
    {
      "downloads": 11314,
      "day": "2024-05-05"
    },
    {
      "downloads": 33316,
      "day": "2024-05-12"
    },
    {
      "downloads": 11586,
      "day": "2024-05-19"
    },
    {
      "downloads": 13695,
      "day": "2024-05-26"
    },
    {
      "downloads": 13553,
      "day": "2024-06-02"
    },
    {
      "downloads": 9702,
      "day": "2024-06-09"
    },
    {
      "downloads": 9468,
      "day": "2024-06-16"
    },
    {
      "downloads": 11016,
      "day": "2024-06-23"
    },
    {
      "downloads": 16213,
      "day": "2024-06-30"
    },
    {
      "downloads": 9966,
      "day": "2024-07-07"
    },
    {
      "downloads": 21750,
      "day": "2024-07-14"
    },
    {
      "downloads": 28343,
      "day": "2024-07-21"
    },
    {
      "downloads": 17239,
      "day": "2024-07-28"
    },
    {
      "downloads": 15069,
      "day": "2024-08-04"
    },
    {
      "downloads": 12043,
      "day": "2024-08-11"
    },
    {
      "downloads": 12022,
      "day": "2024-08-18"
    },
    {
      "downloads": 11195,
      "day": "2024-08-25"
    },
    {
      "downloads": 22125,
      "day": "2024-09-01"
    },
    {
      "downloads": 10596,
      "day": "2024-09-08"
    },
    {
      "downloads": 8847,
      "day": "2024-09-15"
    },
    {
      "downloads": 10297,
      "day": "2024-09-22"
    },
    {
      "downloads": 10837,
      "day": "2024-09-29"
    },
    {
      "downloads": 10655,
      "day": "2024-10-06"
    },
    {
      "downloads": 11019,
      "day": "2024-10-13"
    },
    {
      "downloads": 12043,
      "day": "2024-10-20"
    },
    {
      "downloads": 9590,
      "day": "2024-10-27"
    },
    {
      "downloads": 10325,
      "day": "2024-11-03"
    }
  ]
}