{
  "start": "2024-12-20",
  "end": "2024-12-27",
  "package": "materialize-css",
  "downloads": [
    {
      "downloads": 3315,
      "day": "2024-12-20"
    },
    {
      "downloads": 432,
      "day": "2024-12-21"
    },
    {
      "downloads": 566,
      "day": "2024-12-22"
    },
    {
      "downloads": 2440,
      "day": "2024-12-23"
    },
    {
      "downloads": 1604,
      "day": "2024-12-24"
    },
    {
      "downloads": 790,
      "day": "2024-12-25"
    },
    {
      "downloads": 1642,
      "day": "2024-12-26"
    },
    {
      "downloads": 1604,
      "day": "2024-12-27"
    }
  ]
}