{
  "start": "2024-09-09",
  "end": "2024-09-16",
  "package": "d3-transition",
  "downloads": [
    {
      "downloads": 792930,
      "day": "2024-09-09"
    },
    {
      "downloads": 820185,
      "day": "2024-09-10"
    },
    {
      "downloads": 815165,
      "day": "2024-09-11"
    },
    {
      "downloads": 816668,
      "day": "2024-09-12"
    },
    {
      "downloads": 681361,
      "day": "2024-09-13"
    },
    {
      "downloads": 155396,
      "day": "2024-09-14"
    },
    {
      "downloads": 149061,
      "day": "2024-09-15"
    },
    {
      "downloads": 755635,
      "day": "2024-09-16"
    }
  ]
}