{
  "start": "2023-10-28",
  "end": "2024-10-28",
  "package": "d3-delaunay",
  "downloads": [
    {
      "downloads": 64720,
      "day": "2023-10-28"
    },
    {
      "downloads": 66282,
      "day": "2023-11-04"
    },
    {
      "downloads": 69036,
      "day": "2023-11-11"
    },
    {
      "downloads": 72642,
      "day": "2023-11-18"
    },
    {
      "downloads": 53098,
      "day": "2023-11-25"
    },
    {
      "downloads": 82009,
      "day": "2023-12-02"
    },
    {
      "downloads": 78472,
      "day": "2023-12-09"
    },
    {
      "downloads": 76046,
      "day": "2023-12-16"
    },
    {
      "downloads": 55702,
      "day": "2023-12-23"
    },
    {
      "downloads": 54795,
      "day": "2023-12-30"
    },
    {
      "downloads": 72858,
      "day": "2024-01-06"
    },
    {
      "downloads": 73883,
      "day": "2024-01-13"
    },
    {
      "downloads": 81454,
      "day": "2024-01-20"
    },
    {
      "downloads": 81630,
      "day": "2024-01-27"
    },
    {
      "downloads": 84763,
      "day": "2024-02-03"
    },
    {
      "downloads": 83145,
      "day": "2024-02-10"
    },
    {
      "downloads": 85453,
      "day": "2024-02-17"
    },
    {
      "downloads": 82275,
      "day": "2024-02-24"
    },
    {
      "downloads": 86132,
      "day": "2024-03-02"
    },
    {
      "downloads": 85286,
      "day": "2024-03-09"
    },
    {
      "downloads": 84912,
      "day": "2024-03-16"
    },
    {
      "downloads": 88533,
      "day": "2024-03-23"
    },
    {
      "downloads": 72864,
      "day": "2024-03-30"
    },
    {
      "downloads": 80355,
      "day": "2024-04-06"
    },
    {
      "downloads": 81846,
      "day": "2024-04-13"
    },
    {
      "downloads": 81516,
      "day": "2024-04-20"
    },
    {
      "downloads": 103594,
      "day": "2024-04-27"
    },
    {
      "downloads": 90355,
      "day": "2024-05-04"
    },
    {
      "downloads": 95586,
      "day": "2024-05-11"
    },
    {
      "downloads": 91794,
      "day": "2024-05-18"
    },
    {
      "downloads": 88874,
      "day": "2024-05-25"
    },
    {
      "downloads": 118586,
      "day": "2024-06-01"
    },
    {
      "downloads": 94241,
      "day": "2024-06-08"
    },
    {
      "downloads": 90868,
      "day": "2024-06-15"
    },
    {
      "downloads": 90994,
      "day": "2024-06-22"
    },
    {
      "downloads": 87723,
      "day": "2024-06-29"
    },
    {
      "downloads": 82892,
      "day": "2024-07-06"
    },
    {
      "downloads": 116281,
      "day": "2024-07-13"
    },
    {
      "downloads": 134998,
      "day": "2024-07-20"
    },
    {
      "downloads": 93720,
      "day": "2024-07-27"
    },
    {
      "downloads": 92905,
      "day": "2024-08-03"
    },
    {
      "downloads": 93219,
      "day": "2024-08-10"
    },
    {
      "downloads": 94751,
      "day": "2024-08-17"
    },
    {
      "downloads": 95983,
      "day": "2024-08-24"
    },
    {
      "downloads": 104057,
      "day": "2024-08-31"
    },
    {
      "downloads": 104758,
      "day": "2024-09-07"
    },
    {
      "downloads": 101469,
      "day": "2024-09-14"
    },
    {
      "downloads": 100586,
      "day": "2024-09-21"
    },
    {
      "downloads": 101875,
      "day": "2024-09-28"
    },
    {
      "downloads": 120947,
      "day": "2024-10-05"
    },
    {
      "downloads": 107674,
      "day": "2024-10-12"
    },
    {
      "downloads": 104628,
      "day": "2024-10-19"
    },
    {
      "downloads": 108820,
      "day": "2024-10-26"
    }
  ]
}