{
  "start": "2023-10-24",
  "end": "2024-10-24",
  "package": "d3-axis",
  "downloads": [
    {
      "downloads": 388879,
      "day": "2023-10-24"
    },
    {
      "downloads": 393382,
      "day": "2023-10-31"
    },
    {
      "downloads": 420677,
      "day": "2023-11-07"
    },
    {
      "downloads": 413544,
      "day": "2023-11-14"
    },
    {
      "downloads": 418087,
      "day": "2023-11-21"
    },
    {
      "downloads": 409074,
      "day": "2023-11-28"
    },
    {
      "downloads": 414962,
      "day": "2023-12-05"
    },
    {
      "downloads": 420369,
      "day": "2023-12-12"
    },
    {
      "downloads": 390511,
      "day": "2023-12-19"
    },
    {
      "downloads": 150814,
      "day": "2023-12-26"
    },
    {
      "downloads": 281258,
      "day": "2024-01-02"
    },
    {
      "downloads": 413296,
      "day": "2024-01-09"
    },
    {
      "downloads": 417096,
      "day": "2024-01-16"
    },
    {
      "downloads": 451850,
      "day": "2024-01-23"
    },
    {
      "downloads": 445469,
      "day": "2024-01-30"
    },
    {
      "downloads": 456973,
      "day": "2024-02-06"
    },
    {
      "downloads": 450386,
      "day": "2024-02-13"
    },
    {
      "downloads": 450654,
      "day": "2024-02-20"
    },
    {
      "downloads": 479916,
      "day": "2024-02-27"
    },
    {
      "downloads": 482008,
      "day": "2024-03-05"
    },
    {
      "downloads": 474795,
      "day": "2024-03-12"
    },
    {
      "downloads": 490872,
      "day": "2024-03-19"
    },
    {
      "downloads": 333531,
      "day": "2024-03-26"
    },
    {
      "downloads": 461962,
      "day": "2024-04-02"
    },
    {
      "downloads": 441550,
      "day": "2024-04-09"
    },
    {
      "downloads": 490252,
      "day": "2024-04-16"
    },
    {
      "downloads": 461129,
      "day": "2024-04-23"
    },
    {
      "downloads": 471347,
      "day": "2024-04-30"
    },
    {
      "downloads": 474979,
      "day": "2024-05-07"
    },
    {
      "downloads": 491227,
      "day": "2024-05-14"
    },
    {
      "downloads": 504326,
      "day": "2024-05-21"
    },
    {
      "downloads": 484349,
      "day": "2024-05-28"
    },
    {
      "downloads": 513007,
      "day": "2024-06-04"
    },
    {
      "downloads": 507475,
      "day": "2024-06-11"
    },
    {
      "downloads": 516973,
      "day": "2024-06-18"
    },
    {
      "downloads": 492432,
      "day": "2024-06-25"
    },
    {
      "downloads": 487928,
      "day": "2024-07-02"
    },
    {
      "downloads": 522108,
      "day": "2024-07-09"
    },
    {
      "downloads": 519840,
      "day": "2024-07-16"
    },
    {
      "downloads": 524585,
      "day": "2024-07-23"
    },
    {
      "downloads": 523905,
      "day": "2024-07-30"
    },
    {
      "downloads": 516744,
      "day": "2024-08-06"
    },
    {
      "downloads": 519388,
      "day": "2024-08-13"
    },
    {
      "downloads": 522529,
      "day": "2024-08-20"
    },
    {
      "downloads": 543219,
      "day": "2024-08-27"
    },
    {
      "downloads": 537864,
      "day": "2024-09-03"
    },
    {
      "downloads": 562022,
      "day": "2024-09-10"
    },
    {
      "downloads": 536912,
      "day": "2024-09-17"
    },
    {
      "downloads": 573780,
      "day": "2024-09-24"
    },
    {
      "downloads": 545789,
      "day": "2024-10-01"
    },
    {
      "downloads": 555547,
      "day": "2024-10-08"
    },
    {
      "downloads": 557849,
      "day": "2024-10-15"
    },
    {
      "downloads": 563776,
      "day": "2024-10-22"
    }
  ]
}