{
  "start": "2025-04-25",
  "end": "2025-05-02",
  "package": "unocss",
  "downloads": [
    {
      "downloads": 36469,
      "day": "2025-04-25"
    },
    {
      "downloads": 13226,
      "day": "2025-04-26"
    },
    {
      "downloads": 15791,
      "day": "2025-04-27"
    },
    {
      "downloads": 37304,
      "day": "2025-04-28"
    },
    {
      "downloads": 38463,
      "day": "2025-04-29"
    },
    {
      "downloads": 38401,
      "day": "2025-04-30"
    },
    {
      "downloads": 23705,
      "day": "2025-05-01"
    },
    {
      "downloads": 27104,
      "day": "2025-05-02"
    }
  ]
}