{
  "start": "2024-09-14",
  "end": "2024-09-21",
  "package": "d3-geo",
  "downloads": [
    {
      "downloads": 153761,
      "day": "2024-09-14"
    },
    {
      "downloads": 142661,
      "day": "2024-09-15"
    },
    {
      "downloads": 758305,
      "day": "2024-09-16"
    },
    {
      "downloads": 781176,
      "day": "2024-09-17"
    },
    {
      "downloads": 811323,
      "day": "2024-09-18"
    },
    {
      "downloads": 773730,
      "day": "2024-09-19"
    },
    {
      "downloads": 695343,
      "day": "2024-09-20"
    },
    {
      "downloads": 151860,
      "day": "2024-09-21"
    }
  ]
}