{
  "start": "2024-10-24",
  "end": "2024-10-31",
  "package": "d3-color",
  "downloads": [
    {
      "downloads": 1507074,
      "day": "2024-10-24"
    },
    {
      "downloads": 1341222,
      "day": "2024-10-25"
    },
    {
      "downloads": 292136,
      "day": "2024-10-26"
    },
    {
      "downloads": 296992,
      "day": "2024-10-27"
    },
    {
      "downloads": 1488849,
      "day": "2024-10-28"
    },
    {
      "downloads": 1586380,
      "day": "2024-10-29"
    },
    {
      "downloads": 1562595,
      "day": "2024-10-30"
    },
    {
      "downloads": 1432230,
      "day": "2024-10-31"
    }
  ]
}