{
  "start": "2024-09-26",
  "end": "2024-10-03",
  "package": "bun",
  "downloads": [
    {
      "downloads": 39212,
      "day": "2024-09-26"
    },
    {
      "downloads": 31467,
      "day": "2024-09-27"
    },
    {
      "downloads": 11561,
      "day": "2024-09-28"
    },
    {
      "downloads": 10698,
      "day": "2024-09-29"
    },
    {
      "downloads": 32463,
      "day": "2024-09-30"
    },
    {
      "downloads": 33702,
      "day": "2024-10-01"
    },
    {
      "downloads": 32151,
      "day": "2024-10-02"
    },
    {
      "downloads": 30345,
      "day": "2024-10-03"
    }
  ]
}