{
  "start": "2024-05-02",
  "end": "2025-05-02",
  "package": "@visx/responsive",
  "downloads": [
    {
      "downloads": 74651,
      "day": "2024-05-02"
    },
    {
      "downloads": 71958,
      "day": "2024-05-09"
    },
    {
      "downloads": 89935,
      "day": "2024-05-16"
    },
    {
      "downloads": 83927,
      "day": "2024-05-23"
    },
    {
      "downloads": 84621,
      "day": "2024-05-30"
    },
    {
      "downloads": 78246,
      "day": "2024-06-06"
    },
    {
      "downloads": 76005,
      "day": "2024-06-13"
    },
    {
      "downloads": 72658,
      "day": "2024-06-20"
    },
    {
      "downloads": 78386,
      "day": "2024-06-27"
    },
    {
      "downloads": 46769,
      "day": "2024-07-04"
    },
    {
      "downloads": 72648,
      "day": "2024-07-11"
    },
    {
      "downloads": 83979,
      "day": "2024-07-18"
    },
    {
      "downloads": 80608,
      "day": "2024-07-25"
    },
    {
      "downloads": 82924,
      "day": "2024-08-01"
    },
    {
      "downloads": 84656,
      "day": "2024-08-08"
    },
    {
      "downloads": 67420,
      "day": "2024-08-15"
    },
    {
      "downloads": 75499,
      "day": "2024-08-22"
    },
    {
      "downloads": 77400,
      "day": "2024-08-29"
    },
    {
      "downloads": 67234,
      "day": "2024-09-05"
    },
    {
      "downloads": 70352,
      "day": "2024-09-12"
    },
    {
      "downloads": 65340,
      "day": "2024-09-19"
    },
    {
      "downloads": 73407,
      "day": "2024-09-26"
    },
    {
      "downloads": 63586,
      "day": "2024-10-03"
    },
    {
      "downloads": 72410,
      "day": "2024-10-10"
    },
    {
      "downloads": 70008,
      "day": "2024-10-17"
    },
    {
      "downloads": 69754,
      "day": "2024-10-24"
    },
    {
      "downloads": 72397,
      "day": "2024-10-31"
    },
    {
      "downloads": 73976,
      "day": "2024-11-07"
    },
    {
      "downloads": 65309,
      "day": "2024-11-14"
    },
    {
      "downloads": 77422,
      "day": "2024-11-21"
    },
    {
      "downloads": 50604,
      "day": "2024-11-28"
    },
    {
      "downloads": 75456,
      "day": "2024-12-05"
    },
    {
      "downloads": 75002,
      "day": "2024-12-12"
    },
    {
      "downloads": 74519,
      "day": "2024-12-19"
    },
    {
      "downloads": 21993,
      "day": "2024-12-26"
    },
    {
      "downloads": 37573,
      "day": "2025-01-02"
    },
    {
      "downloads": 65100,
      "day": "2025-01-09"
    },
    {
      "downloads": 71487,
      "day": "2025-01-16"
    },
    {
      "downloads": 68624,
      "day": "2025-01-23"
    },
    {
      "downloads": 69750,
      "day": "2025-01-30"
    },
    {
      "downloads": 68581,
      "day": "2025-02-06"
    },
    {
      "downloads": 74427,
      "day": "2025-02-13"
    },
    {
      "downloads": 71386,
      "day": "2025-02-20"
    },
    {
      "downloads": 78929,
      "day": "2025-02-27"
    },
    {
      "downloads": 75073,
      "day": "2025-03-06"
    },
    {
      "downloads": 78081,
      "day": "2025-03-13"
    },
    {
      "downloads": 71614,
      "day": "2025-03-20"
    },
    {
      "downloads": 70095,
      "day": "2025-03-27"
    },
    {
      "downloads": 74295,
      "day": "2025-04-03"
    },
    {
      "downloads": 68724,
      "day": "2025-04-10"
    },
    {
      "downloads": 85116,
      "day": "2025-04-17"
    },
    {
      "downloads": 83499,
      "day": "2025-04-24"
    },
    {
      "downloads": 73228,
      "day": "2025-05-01"
    }
  ]
}