{
  "start": "2024-10-01",
  "end": "2024-10-08",
  "package": "d3-hierarchy",
  "downloads": [
    {
      "downloads": 734997,
      "day": "2024-10-01"
    },
    {
      "downloads": 663180,
      "day": "2024-10-02"
    },
    {
      "downloads": 664206,
      "day": "2024-10-03"
    },
    {
      "downloads": 612483,
      "day": "2024-10-04"
    },
    {
      "downloads": 153083,
      "day": "2024-10-05"
    },
    {
      "downloads": 149882,
      "day": "2024-10-06"
    },
    {
      "downloads": 715598,
      "day": "2024-10-07"
    },
    {
      "downloads": 745323,
      "day": "2024-10-08"
    }
  ]
}