{
  "start": "2024-09-14",
  "end": "2024-09-21",
  "package": "@visx/network",
  "downloads": [
    {
      "downloads": 787,
      "day": "2024-09-14"
    },
    {
      "downloads": 676,
      "day": "2024-09-15"
    },
    {
      "downloads": 9127,
      "day": "2024-09-16"
    },
    {
      "downloads": 9064,
      "day": "2024-09-17"
    },
    {
      "downloads": 9177,
      "day": "2024-09-18"
    },
    {
      "downloads": 9978,
      "day": "2024-09-19"
    },
    {
      "downloads": 7194,
      "day": "2024-09-20"
    },
    {
      "downloads": 1013,
      "day": "2024-09-21"
    }
  ]
}