{
  "start": "2024-10-24",
  "end": "2024-10-31",
  "package": "d3-dsv",
  "downloads": [
    {
      "downloads": 628815,
      "day": "2024-10-24"
    },
    {
      "downloads": 628763,
      "day": "2024-10-25"
    },
    {
      "downloads": 134697,
      "day": "2024-10-26"
    },
    {
      "downloads": 124112,
      "day": "2024-10-27"
    },
    {
      "downloads": 642138,
      "day": "2024-10-28"
    },
    {
      "downloads": 721946,
      "day": "2024-10-29"
    },
    {
      "downloads": 683903,
      "day": "2024-10-30"
    },
    {
      "downloads": 624967,
      "day": "2024-10-31"
    }
  ]
}