{
  "start": "2024-10-01",
  "end": "2024-10-08",
  "package": "tachyons",
  "downloads": [
    {
      "downloads": 17150,
      "day": "2024-10-01"
    },
    {
      "downloads": 13932,
      "day": "2024-10-02"
    },
    {
      "downloads": 12525,
      "day": "2024-10-03"
    },
    {
      "downloads": 10511,
      "day": "2024-10-04"
    },
    {
      "downloads": 2477,
      "day": "2024-10-05"
    },
    {
      "downloads": 2477,
      "day": "2024-10-06"
    },
    {
      "downloads": 11156,
      "day": "2024-10-07"
    },
    {
      "downloads": 13008,
      "day": "2024-10-08"
    }
  ]
}