{
  "start": "2024-10-14",
  "end": "2024-10-21",
  "package": "@visx/shape",
  "downloads": [
    {
      "downloads": 74180,
      "day": "2024-10-14"
    },
    {
      "downloads": 94572,
      "day": "2024-10-15"
    },
    {
      "downloads": 95384,
      "day": "2024-10-16"
    },
    {
      "downloads": 91570,
      "day": "2024-10-17"
    },
    {
      "downloads": 80115,
      "day": "2024-10-18"
    },
    {
      "downloads": 16218,
      "day": "2024-10-19"
    },
    {
      "downloads": 16271,
      "day": "2024-10-20"
    },
    {
      "downloads": 84850,
      "day": "2024-10-21"
    }
  ]
}