{
  "start": "2024-09-04",
  "end": "2024-09-11",
  "package": "@visx/shape",
  "downloads": [
    {
      "downloads": 97535,
      "day": "2024-09-04"
    },
    {
      "downloads": 90347,
      "day": "2024-09-05"
    },
    {
      "downloads": 80106,
      "day": "2024-09-06"
    },
    {
      "downloads": 16708,
      "day": "2024-09-07"
    },
    {
      "downloads": 14735,
      "day": "2024-09-08"
    },
    {
      "downloads": 89677,
      "day": "2024-09-09"
    },
    {
      "downloads": 98503,
      "day": "2024-09-10"
    },
    {
      "downloads": 92403,
      "day": "2024-09-11"
    }
  ]
}