{
  "start": "2024-10-08",
  "end": "2024-10-15",
  "package": "victory",
  "downloads": [
    {
      "downloads": 42947,
      "day": "2024-10-08"
    },
    {
      "downloads": 46770,
      "day": "2024-10-09"
    },
    {
      "downloads": 48119,
      "day": "2024-10-10"
    },
    {
      "downloads": 39917,
      "day": "2024-10-11"
    },
    {
      "downloads": 6260,
      "day": "2024-10-12"
    },
    {
      "downloads": 5835,
      "day": "2024-10-13"
    },
    {
      "downloads": 37815,
      "day": "2024-10-14"
    },
    {
      "downloads": 46608,
      "day": "2024-10-15"
    }
  ]
}